README.md
pyproject.toml
setup.cfg
setup.py
ancientgreek/__init__.py
ancientgreek/agile.py
ancientgreek/cltk.py
ancientgreek/lexicon.py
ancientgreek.egg-info/PKG-INFO
ancientgreek.egg-info/SOURCES.txt
ancientgreek.egg-info/dependency_links.txt
ancientgreek.egg-info/requires.txt
ancientgreek.egg-info/top_level.txt