Metadata-Version: 2.1
Name: ancientgreek
Version: 0.2.1
Summary: AGILe, Ancient Greek Inscriptions Lemmatizer
Home-page: https://github.com/agile-gronlp/agile/
Author: Jasper K. Bos
Author-email: Silvia Stopponi <s.stopponi@rug.nl>
Project-URL: Homepage, https://github.com/agile-gronlp/agile/
Project-URL: Issues, https://github.com/agile-gronlp/agile/issues
Classifier: Programming Language :: Python :: 3
Classifier: License :: OSI Approved :: MIT License
Classifier: Operating System :: OS Independent
Requires-Python: >=3.0
